azure/mgmt/hybridcompute/__init__.py
azure/mgmt/hybridcompute/_configuration.py
azure/mgmt/hybridcompute/_hybrid_compute_management_client.py
azure/mgmt/hybridcompute/_patch.py
azure/mgmt/hybridcompute/_serialization.py
azure/mgmt/hybridcompute/_vendor.py
azure/mgmt/hybridcompute/_version.py
azure/mgmt/hybridcompute/py.typed
azure/mgmt/hybridcompute/aio/__init__.py
azure/mgmt/hybridcompute/aio/_configuration.py
azure/mgmt/hybridcompute/aio/_hybrid_compute_management_client.py
azure/mgmt/hybridcompute/aio/_patch.py
azure/mgmt/hybridcompute/aio/_vendor.py
azure/mgmt/hybridcompute/aio/operations/__init__.py
azure/mgmt/hybridcompute/aio/operations/_extension_metadata_operations.py
azure/mgmt/hybridcompute/aio/operations/_hybrid_compute_management_client_operations.py
azure/mgmt/hybridcompute/aio/operations/_license_profiles_operations.py
azure/mgmt/hybridcompute/aio/operations/_licenses_operations.py
azure/mgmt/hybridcompute/aio/operations/_machine_extensions_operations.py
azure/mgmt/hybridcompute/aio/operations/_machines_operations.py
azure/mgmt/hybridcompute/aio/operations/_network_profile_operations.py
azure/mgmt/hybridcompute/aio/operations/_network_security_perimeter_configurations_operations.py
azure/mgmt/hybridcompute/aio/operations/_operations.py
azure/mgmt/hybridcompute/aio/operations/_patch.py
azure/mgmt/hybridcompute/aio/operations/_private_endpoint_connections_operations.py
azure/mgmt/hybridcompute/aio/operations/_private_link_resources_operations.py
azure/mgmt/hybridcompute/aio/operations/_private_link_scopes_operations.py
azure/mgmt/hybridcompute/models/__init__.py
azure/mgmt/hybridcompute/models/_hybrid_compute_management_client_enums.py
azure/mgmt/hybridcompute/models/_models_py3.py
azure/mgmt/hybridcompute/models/_patch.py
azure/mgmt/hybridcompute/operations/__init__.py
azure/mgmt/hybridcompute/operations/_extension_metadata_operations.py
azure/mgmt/hybridcompute/operations/_hybrid_compute_management_client_operations.py
azure_mgmt_hybridcompute-9.0.0.dist-info/LICENSE
azure_mgmt_hybridcompute-9.0.0.dist-info/METADATA
azure_mgmt_hybridcompute-9.0.0.dist-info/WHEEL
azure_mgmt_hybridcompute-9.0.0.dist-info/top_level.txt
azure_mgmt_hybridcompute-9.0.0.dist-info/RECORD
